LICENSE.txt
MANIFEST.in
README.rst
mboxattachments.py
setup.cfg
setup.py
bin/mboxattachments
mboxattachments.egg-info/PKG-INFO
mboxattachments.egg-info/SOURCES.txt
mboxattachments.egg-info/dependency_links.txt
mboxattachments.egg-info/entry_points.txt
mboxattachments.egg-info/requires.txt
mboxattachments.egg-info/top_level.txt