Metadata-Version: 1.1
Name: mboxattachments
Version: 0.5.35
Summary: Utility for exporting attachments from mbox files
Home-page: http://www.chuck-jackson-photos.com/mboxattachments
Author: Charles L Jackson
Author-email: chuckj44@gmail.com
License: MIT
Keywords: mbox attachments extract email photos images
Platform: UNKNOWN
Classifier: Development Status :: 4 - Beta
Classifier: Intended Audience :: End Users/Desktop
Classifier: Topic :: Communications :: Email
Classifier: License :: OSI Approved :: MIT License
Classifier: Programming Language :: Python :: 3
Classifier: Programming Language :: Python :: 3.3
Classifier: Programming Language :: Python :: 3.4
Classifier: Programming Language :: Python :: 3.5
